data_objects/__init__.py
data_objects/customer.py
data_objects/geometry_with_attributes_table.py
data_objects/order.py
data_objects/product.py
data_objects/resolution.py
data_objects/task_graph.py
data_objects/task_info.py
terranova_dataclasses_library-0.1.0.dist-info/METADATA
terranova_dataclasses_library-0.1.0.dist-info/WHEEL
terranova_dataclasses_library-0.1.0.dist-info/top_level.txt
terranova_dataclasses_library-0.1.0.dist-info/RECORD
